tdict/__init__.py
tdict/tdict.py
tdict-0.4.6.1.dist-info/LICENSE
tdict-0.4.6.1.dist-info/METADATA
tdict-0.4.6.1.dist-info/WHEEL
tdict-0.4.6.1.dist-info/top_level.txt
tdict-0.4.6.1.dist-info/RECORD
