Metadata-Version: 2.1
Name: tdict
Version: 0.4.6.1
Summary: Tree-structured dict for easy handling of configurations and results
Home-page: https://github.com/royf/tdict
Author: Roy Fox
Author-email: roy.d.fox@gmail.com
License: MIT
License-File: LICENSE
